LICENSE
asyncio_chainable/__init__.py
asyncio_chainable/chainable.py
asyncio_chainable-0.1.3.dist-info/LICENSE
asyncio_chainable-0.1.3.dist-info/WHEEL
asyncio_chainable-0.1.3.dist-info/METADATA
asyncio_chainable-0.1.3.dist-info/RECORD
