Metadata-Version: 2.1
Name: asyncio-chainable
Version: 0.1.3
Summary: Making asyncio coroutines chainable
Home-page: https://github.com/sihrc/asyncio-chainable
License: MIT
Keywords: asyncio
Author: Chris Lee
Author-email: sihrc.c.lee@gmail.com
Requires-Python: >=3.7,<4.0
Classifier: License :: OSI Approved :: MIT License
Classifier: Programming Language :: Python :: 3
Classifier: Programming Language :: Python :: 3.10
Classifier: Programming Language :: Python :: 3.7
Classifier: Programming Language :: Python :: 3.8
Classifier: Programming Language :: Python :: 3.9
Requires-Dist: setuptools (>=57.4.0,<58.0.0)
Project-URL: Repository, https://github.com/sihrc/asyncio-chainable
